LICENSE
README.md
setup.py
hc_fib_pay/__init__.py
hc_fib_pay.egg-info/PKG-INFO
hc_fib_pay.egg-info/SOURCES.txt
hc_fib_pay.egg-info/dependency_links.txt
hc_fib_pay.egg-info/entry_points.txt
hc_fib_pay.egg-info/top_level.txt
hc_fib_pay/cmd/__init__.py
hc_fib_pay/cmd/fib_numb.py
hc_fib_pay/fib_calcs/__init__.py
hc_fib_pay/fib_calcs/fib_number.py
hc_fib_pay/fib_calcs/fib_numbers.py
hc_fib_pay/tests/__init__.py
hc_fib_pay/tests/hc_fib_pay/__init__.py
hc_fib_pay/tests/hc_fib_pay/fib_calcs/__init__.py
hc_fib_pay/tests/hc_fib_pay/fib_calcs/test_fib_number.py
hc_fib_pay/tests/hc_fib_pay/fib_calcs/test_fib_numbers.py