Metadata-Version: 2.1
Name: hc-fib-pay
Version: 0.0.1
Summary: Calculates a Fibonacci number
Home-page: https://github.com/hoichong/hc-fib-pay
Author: HC
Author-email: chonghoiyuen@gmail.com
Classifier: Development Status :: 4 - Beta
Classifier: Programming Language :: Python :: 3
Classifier: Operating System :: OS Independent
Requires-Python: >=3
License-File: LICENSE
